sievepy
