Metadata-Version: 2.1
Name: sievepy
Version: 1.0.4
Summary: A package which efficiently finds the prime numbers
Home-page: https://github.com/Abhilash11Addanki/Sievepy
Author: Abhilash
Author-email: abhilash11addanki@gmail.com
License: MIT
Keywords: configuration core yaml ini json environment
Platform: UNKNOWN
Classifier: Programming Language :: Python :: 3
Classifier: License :: OSI Approved :: MIT License
Classifier: Operating System :: OS Independent
Requires-Python: >=3.6
